MANIFEST.in
README.rst
requirements.txt
setup.cfg
setup.py
myql/__init__.py
myql/errors.py
myql/myql.py
myql/utils.py
myql.egg-info/PKG-INFO
myql.egg-info/SOURCES.txt
myql.egg-info/dependency_links.txt
myql.egg-info/requires.txt
myql.egg-info/top_level.txt
myql/contrib/__init__.py
myql/contrib/finance/__init__.py
myql/contrib/finance/stockscraper/__init__.py
myql/contrib/finance/stockscraper/stockretriever.py
myql/contrib/table/__init__.py
myql/contrib/table/base.py
myql/contrib/table/binder.py
myql/contrib/table/exceptions.py
myql/contrib/table/table.py
myql/contrib/weather/__init__.py
myql/contrib/weather/weather.py
tests/__init__.py
tests/tests.py