Metadata-Version: 1.1
Name: myql
Version: 1.2.6
Summary: Python Wrapper for the Yahoo! Query Language. Allowing to run YQL queries, fetch financial data and create YQL Open Tables
Home-page: https://github.com/josuebrunel/MYQL
Author: Josue Kouka
Author-email: josuebrunel@gmail.com
License: MIT
Download-URL: https://github.com/josuebrunel/myql/archive/1.2.6.tar.gz
Keywords: myql,yql,yahoo,query,language
Platform: Any
Classifier: Programming Language :: Python
Classifier: Programming Language :: Python :: 2
Classifier: Programming Language :: Python :: 2.7
Classifier: Programming Language :: Python :: 3
Classifier: Programming Language :: Python :: 3.2
Classifier: Programming Language :: Python :: 3.3
Classifier: Programming Language :: Python :: 3.4
Classifier: Programming Language :: Python :: Implementation :: CPython
Classifier: Programming Language :: Python :: Implementation :: PyPy
Classifier: Development Status :: 5 - Production/Stable
Classifier: Topic :: Software Development :: Libraries :: Python Modules
Classifier: Environment :: Console
Classifier: Intended Audience :: Developers
Classifier: License :: OSI Approved :: MIT License
